<?xml version="1.0" ?><annotation verified="yes">
	<folder>airplane</folder>
	<filename>201112080459349839.jpg</filename>
	<path>F:\airplane\201112080459349839.jpg</path>
	<source>
		<database>Unknown</database>
	</source>
	<size>
		<width>2787</width>
		<height>1895</height>
		<depth>3</depth>
	</size>
	<segmented>0</segmented>
	<object>
		<name>airplane</name>
		<pose>Unspecified</pose>
		<truncated>0</truncated>
		<difficult>0</difficult>
		<bndbox>
			<xmin>102</xmin>
			<ymin>496</ymin>
			<xmax>2643</xmax>
			<ymax>1269</ymax>
		</bndbox>
	</object>
	<object>
		<name>person</name>
		<pose>Unspecified</pose>
		<truncated>0</truncated>
		<difficult>0</difficult>
		<bndbox>
			<xmin>2181</xmin>
			<ymin>1122</ymin>
			<xmax>2396</xmax>
			<ymax>1481</ymax>
		</bndbox>
	</object>
	<object>
		<name>person</name>
		<pose>Unspecified</pose>
		<truncated>0</truncated>
		<difficult>0</difficult>
		<bndbox>
			<xmin>1222</xmin>
			<ymin>1081</ymin>
			<xmax>1393</xmax>
			<ymax>1413</ymax>
		</bndbox>
	</object>
	<object>
		<name>person</name>
		<pose>Unspecified</pose>
		<truncated>0</truncated>
		<difficult>0</difficult>
		<bndbox>
			<xmin>858</xmin>
			<ymin>1028</ymin>
			<xmax>996</xmax>
			<ymax>1366</ymax>
		</bndbox>
	</object>
	<object>
		<name>person</name>
		<pose>Unspecified</pose>
		<truncated>0</truncated>
		<difficult>0</difficult>
		<bndbox>
			<xmin>758</xmin>
			<ymin>1078</ymin>
			<xmax>884</xmax>
			<ymax>1393</ymax>
		</bndbox>
	</object>
	<object>
		<name>person</name>
		<pose>Unspecified</pose>
		<truncated>0</truncated>
		<difficult>0</difficult>
		<bndbox>
			<xmin>681</xmin>
			<ymin>1022</ymin>
			<xmax>784</xmax>
			<ymax>1387</ymax>
		</bndbox>
	</object>
	<object>
		<name>person</name>
		<pose>Unspecified</pose>
		<truncated>0</truncated>
		<difficult>0</difficult>
		<bndbox>
			<xmin>567</xmin>
			<ymin>1066</ymin>
			<xmax>687</xmax>
			<ymax>1372</ymax>
		</bndbox>
	</object>
	<object>
		<name>person</name>
		<pose>Unspecified</pose>
		<truncated>0</truncated>
		<difficult>0</difficult>
		<bndbox>
			<xmin>340</xmin>
			<ymin>1007</ymin>
			<xmax>508</xmax>
			<ymax>1352</ymax>
		</bndbox>
	</object>
	<object>
		<name>person</name>
		<pose>Unspecified</pose>
		<truncated>0</truncated>
		<difficult>0</difficult>
		<bndbox>
			<xmin>181</xmin>
			<ymin>1025</ymin>
			<xmax>290</xmax>
			<ymax>1290</ymax>
		</bndbox>
	</object>
</annotation>