<annotation verified="yes">
	<folder>airplane</folder>
	<filename>201205040656237186.jpg</filename>
	<path>F:\airplane\201205040656237186.jpg</path>
	<source>
		<database>Unknown</database>
	</source>
	<size>
		<width>2160</width>
		<height>1664</height>
		<depth>3</depth>
	</size>
	<segmented>0</segmented>
	<object>
		<name>airplane</name>
		<pose>Unspecified</pose>
		<truncated>1</truncated>
		<difficult>0</difficult>
		<bndbox>
			<xmin>16</xmin>
			<ymin>218</ymin>
			<xmax>2160</xmax>
			<ymax>1492</ymax>
		</bndbox>
	</object>
</annotation>
