<?xml version="1.0" ?><annotation verified="yes">
	<folder>airplane</folder>
	<filename>8838288dcab846f7bc1356e8e0ea7e29_th.png</filename>
	<path>F:\airplane\8838288dcab846f7bc1356e8e0ea7e29_th.png</path>
	<source>
		<database>Unknown</database>
	</source>
	<size>
		<width>640</width>
		<height>480</height>
		<depth>3</depth>
	</size>
	<segmented>0</segmented>
	<object>
		<name>airplane</name>
		<pose>Unspecified</pose>
		<truncated>0</truncated>
		<difficult>0</difficult>
		<bndbox>
			<xmin>10</xmin>
			<ymin>69</ymin>
			<xmax>636</xmax>
			<ymax>319</ymax>
		</bndbox>
	</object>
</annotation>