<annotation verified="yes">
	<folder>CarDataset&#20891;&#29992;&#36234;&#37326;&#36710;_1</folder>
	<filename>Baidu_1066.jpeg</filename>
	<path>F:\Desktop\CarDataset-&#24453;&#26631;&#27880;\CarDataset&#20891;&#29992;&#36234;&#37326;&#36710;_1\Baidu_1066.jpeg</path>
	<source>
		<database>Unknown</database>
	</source>
	<size>
		<width>139</width>
		<height>90</height>
		<depth>3</depth>
	</size>
	<segmented>0</segmented>
	<object>
		<name>truck</name>
		<pose>Unspecified</pose>
		<truncated>1</truncated>
		<difficult>0</difficult>
		<bndbox>
			<xmin>1</xmin>
			<ymin>6</ymin>
			<xmax>135</xmax>
			<ymax>81</ymax>
		</bndbox>
	</object>
</annotation>