<annotation>
	<folder>CarDataset&#20891;&#29992;&#36234;&#37326;&#36710;_1</folder>
	<filename>Baidu_0496.jpeg</filename>
	<path>F:\Desktop\CarDataset-&#24453;&#26631;&#27880;\CarDataset&#20891;&#29992;&#36234;&#37326;&#36710;_1\Baidu_0496.jpeg</path>
	<source>
		<database>Unknown</database>
	</source>
	<size>
		<width>980</width>
		<height>692</height>
		<depth>3</depth>
	</size>
	<segmented>0</segmented>
	<object>
		<name>off-road_vehicle</name>
		<pose>Unspecified</pose>
		<truncated>0</truncated>
		<difficult>0</difficult>
		<bndbox>
			<xmin>50</xmin>
			<ymin>169</ymin>
			<xmax>779</xmax>
			<ymax>647</ymax>
		</bndbox>
	</object>
	<object>
		<name>off-road_vehicle</name>
		<pose>Unspecified</pose>
		<truncated>0</truncated>
		<difficult>0</difficult>
		<bndbox>
			<xmin>718</xmin>
			<ymin>195</ymin>
			<xmax>905</xmax>
			<ymax>417</ymax>
		</bndbox>
	</object>
	<object>
		<name>person</name>
		<pose>Unspecified</pose>
		<truncated>0</truncated>
		<difficult>0</difficult>
		<bndbox>
			<xmin>235</xmin>
			<ymin>216</ymin>
			<xmax>632</xmax>
			<ymax>283</ymax>
		</bndbox>
	</object>
</annotation>