<?xml version="1.0" ?><annotations><filename>jam8_0032.jpg</filename><folder>images</folder><size><width>2448</width><height>2048</height><depth>3</depth></size><object><name>person</name><pose>Unspecified</pose><truncated>0</truncated><difficult>0</difficult><bndbox><xmin>392</xmin><ymin>909.0</ymin><xmax>486</xmax><ymax>1162.0</ymax></bndbox></object><object><name>person</name><pose>Unspecified</pose><truncated>0</truncated><difficult>0</difficult><bndbox><xmin>202</xmin><ymin>878.0</ymin><xmax>289</xmax><ymax>1115.0</ymax></bndbox></object><object><name>person</name><pose>Unspecified</pose><truncated>0</truncated><difficult>0</difficult><bndbox><xmin>1498</xmin><ymin>840.0</ymin><xmax>1599</xmax><ymax>1060.0</ymax></bndbox></object><object><name>car</name><pose>Unspecified</pose><truncated>0</truncated><difficult>0</difficult><bndbox><xmin>2001</xmin><ymin>452.0</ymin><xmax>2127</xmax><ymax>532.0</ymax></bndbox></object><object><name>car</name><pose>Unspecified</pose><truncated>0</truncated><difficult>0</difficult><bndbox><xmin>1591</xmin><ymin>331.0</ymin><xmax>1658</xmax><ymax>382.0</ymax></bndbox></object><object><name>car</name><pose>Unspecified</pose><truncated>0</truncated><difficult>0</difficult><bndbox><xmin>312</xmin><ymin>484.0</ymin><xmax>435</xmax><ymax>589.0</ymax></bndbox></object><object><name>person</name><pose>Unspecified</pose><truncated>0</truncated><difficult>0</difficult><bndbox><xmin>1058</xmin><ymin>311.0</ymin><xmax>1087</xmax><ymax>364.0</ymax></bndbox></object></annotations>