<?xml version="1.0" ?><annotations><filename>jam6_0111.jpg</filename><folder>images</folder><size><width>2448</width><height>2048</height><depth>3</depth></size><object><name>car</name><pose>Unspecified</pose><truncated>0</truncated><difficult>0</difficult><bndbox><xmin>1649</xmin><ymin>702.0</ymin><xmax>2100</xmax><ymax>956.0</ymax></bndbox></object><object><name>car</name><pose>Unspecified</pose><truncated>0</truncated><difficult>0</difficult><bndbox><xmin>1643</xmin><ymin>949.0</ymin><xmax>2103</xmax><ymax>1352.0</ymax></bndbox></object><object><name>car</name><pose>Unspecified</pose><truncated>0</truncated><difficult>0</difficult><bndbox><xmin>558</xmin><ymin>840.0</ymin><xmax>902</xmax><ymax>1140.0</ymax></bndbox></object><object><name>car</name><pose>Unspecified</pose><truncated>0</truncated><difficult>0</difficult><bndbox><xmin>245</xmin><ymin>1165.0</ymin><xmax>783</xmax><ymax>1627.0</ymax></bndbox></object><object><name>car</name><pose>Unspecified</pose><truncated>0</truncated><difficult>0</difficult><bndbox><xmin>1987</xmin><ymin>1559.0</ymin><xmax>2421</xmax><ymax>2002.0</ymax></bndbox></object><object><name>car</name><pose>Unspecified</pose><truncated>0</truncated><difficult>0</difficult><bndbox><xmin>937</xmin><ymin>559.0</ymin><xmax>1556</xmax><ymax>1527.0</ymax></bndbox></object><object><name>car</name><pose>Unspecified</pose><truncated>0</truncated><difficult>0</difficult><bndbox><xmin>1056</xmin><ymin>249.0</ymin><xmax>1159</xmax><ymax>352.0</ymax></bndbox></object></annotations>