<?xml version="1.0" ?><annotations><filename>jam15_0010.jpg</filename><folder>images</folder><size><width>2048</width><height>1536</height><depth>3</depth></size><object><name>car</name><pose>Unspecified</pose><truncated>0</truncated><difficult>0</difficult><bndbox><xmin>329</xmin><ymin>617.9999999992319</ymin><xmax>1112</xmax><ymax>1476.999999999744</ymax></bndbox></object><object><name>car</name><pose>Unspecified</pose><truncated>0</truncated><difficult>0</difficult><bndbox><xmin>602</xmin><ymin>7.679545888095163e-10</ymin><xmax>1183</xmax><ymax>494.000000000256</ymax></bndbox></object><object><name>car</name><pose>Unspecified</pose><truncated>0</truncated><difficult>0</difficult><bndbox><xmin>1767</xmin><ymin>870.0000000007681</ymin><xmax>2048</xmax><ymax>1535.000000000256</ymax></bndbox></object><object><name>car</name><pose>Unspecified</pose><truncated>0</truncated><difficult>0</difficult><bndbox><xmin>1481</xmin><ymin>-3.071960463785217e-10</ymin><xmax>1945</xmax><ymax>154.0000000002048</ymax></bndbox></object><object><name>car</name><pose>Unspecified</pose><truncated>0</truncated><difficult>0</difficult><bndbox><xmin>1</xmin><ymin>188.99999999923205</ymin><xmax>200</xmax><ymax>1053.999999999744</ymax></bndbox></object></annotations>