<annotations><filename>jam12_0016.jpg</filename><folder>images</folder><size><width>1600</width><height>1200</height><depth>3</depth></size><object><name>person</name><pose>Unspecified</pose><truncated>0</truncated><difficult>0</difficult><bndbox><xmin>199.99999999999997</xmin><ymin>103.00000000020003</ymin><xmax>281.0</xmax><ymax>304.9999999998</ymax></bndbox></object><object><name>person</name><pose>Unspecified</pose><truncated>0</truncated><difficult>0</difficult><bndbox><xmin>1039.0</xmin><ymin>2.4000001985768904e-10</ymin><xmax>1113.0</xmax><ymax>120.99999999983999</ymax></bndbox></object><object><name>car</name><pose>Unspecified</pose><truncated>0</truncated><difficult>0</difficult><bndbox><xmin>587.0</xmin><ymin>-2.3999291443033144e-10</ymin><xmax>759.0</xmax><ymax>149.00000000016001</ymax></bndbox></object><object><name>car</name><pose>Unspecified</pose><truncated>0</truncated><difficult>0</difficult><bndbox><xmin>0.0</xmin><ymin>4.999999999799996</ymin><xmax>127.0</xmax><ymax>160.0000000002</ymax></bndbox></object><object><name>person</name><pose>Unspecified</pose><truncated>0</truncated><difficult>0</difficult><bndbox><xmin>1531.0</xmin><ymin>-6.000533403494046e-11</ymin><xmax>1592.0</xmax><ymax>115.99999999997999</ymax></bndbox></object></annotations>