<?xml version="1.0" ?><annotation verified="yes">
	<folder>tank</folder>
	<filename>Bing_0301.jpeg</filename>
	<path>D:\tank\Bing_0301.jpeg</path>
	<source>
		<database>Unknown</database>
	</source>
	<size>
		<width>950</width>
		<height>632</height>
		<depth>3</depth>
	</size>
	<segmented>0</segmented>
	<object>
		<name>tank</name>
		<pose>Unspecified</pose>
		<truncated>0</truncated>
		<difficult>0</difficult>
		<bndbox>
			<xmin>139</xmin>
			<ymin>109</ymin>
			<xmax>790</xmax>
			<ymax>582</ymax>
		</bndbox>
	</object>
	<object>
		<name>tank</name>
		<pose>Unspecified</pose>
		<truncated>1</truncated>
		<difficult>0</difficult>
		<bndbox>
			<xmin>1</xmin>
			<ymin>309</ymin>
			<xmax>213</xmax>
			<ymax>468</ymax>
		</bndbox>
	</object>
</annotation>