<?xml version="1.0" ?><annotation verified="yes">
	<folder>tank</folder>
	<filename>Bing_0007.jpeg</filename>
	<path>D:\tank\Bing_0007.jpeg</path>
	<source>
		<database>Unknown</database>
	</source>
	<size>
		<width>1024</width>
		<height>794</height>
		<depth>3</depth>
	</size>
	<segmented>0</segmented>
	<object>
		<name>tank</name>
		<pose>Unspecified</pose>
		<truncated>0</truncated>
		<difficult>0</difficult>
		<bndbox>
			<xmin>7</xmin>
			<ymin>180</ymin>
			<xmax>1018</xmax>
			<ymax>756</ymax>
		</bndbox>
	</object>
	<object>
		<name>person</name>
		<pose>Unspecified</pose>
		<truncated>0</truncated>
		<difficult>0</difficult>
		<bndbox>
			<xmin>79</xmin>
			<ymin>361</ymin>
			<xmax>155</xmax>
			<ymax>424</ymax>
		</bndbox>
	</object>
</annotation>